README.md
setup.py
xToolkit/__init__.py
xToolkit.egg-info/PKG-INFO
xToolkit.egg-info/SOURCES.txt
xToolkit.egg-info/dependency_links.txt
xToolkit.egg-info/requires.txt
xToolkit.egg-info/top_level.txt
xToolkit/xdatetime/__init__.py
xToolkit/xdatetime/api.py
xToolkit/xdatetime/xdatetime/__init__.py
xToolkit/xdatetime/xdatetime/xdatetime.py
xToolkit/xfile/__init__.py
xToolkit/xfile/api.py
xToolkit/xfile/dispose/__init__.py
xToolkit/xfile/dispose/dispose.py
xToolkit/xhotchpotch/__init__.py
xToolkit/xhotchpotch/api.py
xToolkit/xhotchpotch/dispose/__init__.py
xToolkit/xhotchpotch/dispose/dispose.py
xToolkit/xlist/__init__.py
xToolkit/xlist/api.py
xToolkit/xlist/dispose/__init__.py
xToolkit/xlist/dispose/dispose.py
xToolkit/xstring/__init__.py
xToolkit/xstring/api.py
xToolkit/xstring/xstring.py
xToolkit/xstring/check/__init__.py
xToolkit/xstring/check/check.py
xToolkit/xstring/dispose/__init__.py
xToolkit/xstring/dispose/dispose.py
xToolkit/xthreading/__init__.py
xToolkit/xthreading/xthread.py
xToolkit/xtoolkit/__init__.py
xToolkit/xtoolkit/judgement.py
xToolkit/xtoolkit/xtoolkit.py