Metadata-Version: 2.1
Name: xToolkit
Version: 0.0.78
Summary: UNKNOWN
Home-page: https://github.com/xionglihong/xToolkit
Author: xionglihong
Author-email: xionglihong@163.com
License: GNU General Public License v3.0
Platform: UNKNOWN
